iva_tpu
