Metadata-Version: 2.1
Name: iva-tpu
Version: 11.0.7
Summary: IVA TPU Python API
Home-page: http://git.mmp.iva-tech.ru/tpu_sw/iva_tpu_sdk
Author: Maxim Moroz
Author-email: m.moroz@iva-tech.ru
License: UNKNOWN
Platform: UNKNOWN
Requires-Python: >=3.6
